{
 "id": "74129835",
 "url": "https://www.vdab.be/vindeenjob/vacatures/74129835/customer-service-coordinator",
 "status": "ready",
 "apply_email": "",
 "email_subject": "Sollicitatie — Customer Service Coördinator",
 "email_body": "Beste,\n\nMet veel enthousiasme reageer ik op de vacature voor Customer Service Coördinator bij ITZU in Maasmechelen. Uw oproep voor een gestructureerde en proactieve professional sluit naadloos aan bij mijn ervaring en vaardigheden.\n\nIn mijn huidige rol als Junior Digital Marketer bij Episto ben ik verantwoordelijk voor het beheren van dossiers, het opvolgen van offertes en facturatie, en het coördineren van werkzaamheden met klanten en leveranciers. Ik werk nauwkeurig en zelfstandig, en schakel moeiteloos tussen dagelijkse taken en ad-hoc opdrachten. Mijn technische achtergrond in webontwikkeling en SEO heeft mij geleerd om processen te optimaliseren en verbeterpunten te signaleren.\n\nIk beheers Word, Excel en Outlook goed, en communiceer vlot in het Nederlands (B1, met lessen om verder te verbeteren). Ik ben gewend om in een dynamische omgeving te werken en haal energie uit een veelzijdige rol.\n\nIk voeg mijn cv en motivatiebrief bij. Ik hoop u in een gesprek verder te overtuigen.\n\nMet vriendelijke groet,\nBaver Ok\n+32 470 42 48 36\nbaverok@gmail.com\nlinkedin.com/in/baverok\n\n--- English version ---\n\nDear,\n\nI am very enthusiastic to apply for the Customer Service Coordinator position at ITZU in Maasmechelen. Your call for a structured and proactive professional aligns perfectly with my experience and skills.\n\nIn my current role as Junior Digital Marketer at Episto, I am responsible for managing files, following up on quotes and invoicing, and coordinating work with clients and suppliers. I work accurately and independently, and switch effortlessly between daily tasks and ad-hoc assignments. My technical background in web development and SEO has taught me to optimize processes and identify areas for improvement.\n\nI am proficient in Word, Excel, and Outlook, and communicate fluently in Dutch (B1, with lessons to improve further). I am used to working in a dynamic environment and thrive in a versatile role.\n\nI attach my CV and motivation letter. I hope to convince you further in an interview.\n\nKind regards,\nBaver Ok\n+32 470 42 48 36\nbaverok@gmail.com\nlinkedin.com/in/baverok",
 "cover_letter": "Beste lezer,\n\nMet veel motivatie solliciteer ik naar de functie van Customer Service Coördinator bij ITZU in Maasmechelen. Uw oproep voor een gestructureerde, proactieve en veelzijdige professional sluit naadloos aan bij mijn ervaring en ambitie.\n\nIn mijn huidige rol als Junior Digital Marketer bij Episto ben ik verantwoordelijk voor de administratieve en operationele ondersteuning van het management. Ik beheer dossiers, volg offertes en facturatie op, en coördineer werkzaamheden met klanten, leveranciers en interne teams. Deze ervaring heeft mij geleerd om overzicht te bewaren, snel te schakelen en processen efficiënt te laten verlopen. Ik werk nauwkeurig en zelfstandig, maar ook collegiaal en oplossingsgericht.\n\nMijn technische achtergrond in webontwikkeling en SEO heeft mij een gestructureerde en analytische denkwijze gegeven. Ik ben gewend om verbeterpunten te signaleren en actief mee te denken over optimalisaties. Daarnaast beheers ik Word, Excel en Outlook goed, en communiceer ik vlot in het Nederlands (B1, met lessen om verder te verbeteren).\n\nWat mij aanspreekt in deze functie is de afwisseling tussen administratieve taken, planning en communicatie. Ik haal energie uit een veelzijdige rol waarin ik verantwoordelijkheid kan nemen en echt impact kan maken. Uw organisatie, actief in de facilitaire sector, biedt een stabiele en groeiende omgeving waar ik mijn organisatorische vaardigheden verder kan ontwikkelen.\n\nIk ben ervan overtuigd dat ik met mijn gestructureerde aanpak, proactiviteit en technische inzicht een waardevolle bijdrage kan leveren aan uw team. Ik hoop u in een persoonlijk gesprek verder te overtuigen.\n\nMet vriendelijke groet,\nBaver Ok\n+32 470 42 48 36\nbaverok@gmail.com\nlinkedin.com/in/baverok\n\n--- English version ---\n\nDear reader,\n\nI am very motivated to apply for the Customer Service Coordinator position at ITZU in Maasmechelen. Your call for a structured, proactive, and versatile professional aligns perfectly with my experience and ambition.\n\nIn my current role as Junior Digital Marketer at Episto, I am responsible for administrative and operational support to management. I manage files, follow up on quotes and invoicing, and coordinate work with clients, suppliers, and internal teams. This experience has taught me to maintain overview, switch quickly, and ensure processes run efficiently. I work accurately and independently, but also collegially and solution-oriented.\n\nMy technical background in web development and SEO has given me a structured and analytical mindset. I am used to identifying areas for improvement and actively thinking about optimizations. Additionally, I am proficient in Word, Excel, and Outlook, and communicate fluently in Dutch (B1, with lessons to improve further).\n\nWhat appeals to me in this role is the variety between administrative tasks, planning, and communication. I thrive in a versatile role where I can take responsibility and truly make an impact. Your organization, active in the facilities sector, offers a stable and growing environment where I can further develop my organizational skills.\n\nI am convinced that with my structured approach, proactivity, and technical insight, I can make a valuable contribution to your team. I hope to convince you further in a personal conversation.\n\nKind regards,\nBaver Ok\n+32 470 42 48 36\nbaverok@gmail.com\nlinkedin.com/in/baverok",
 "cv_highlights": "Administratieve en operationele ondersteuning van management (dossierbeheer, offertes, facturatie)\nCoördinatie met klanten, leveranciers en interne teams als centraal aanspreekpunt\nNauwkeurig, gestructureerd en zelfstandig werken met oog voor procesoptimalisatie\nUitstekende beheersing van Word, Excel en Outlook; vlot Nederlands (B1)\nProactief en oplossingsgericht met technische achtergrond in web en SEO",
 "tailored_cv": "# Baver Ok\nCustomer Service Coördinator · Administratieve & Operationele Ondersteuning\nZwijndrecht, Belgium | +32 470 42 48 36 | baverok@gmail.com | linkedin.com/in/baverok\n\n## Profiel\nJunior professional met ervaring in administratieve en operationele ondersteuning, dossierbeheer en coördinatie. Bij Episto fungeer ik als rechterhand van het management: ik beheer dossiers, volg offertes en facturatie op, en coördineer werkzaamheden met klanten, leveranciers en interne teams. Ik werk gestructureerd, nauwkeurig en zelfstandig, en schakel moeiteloos tussen dagelijkse taken en ad-hoc opdrachten. Daarnaast heb ik een technische achtergrond in webontwikkeling en SEO, wat mij een analytische en oplossingsgerichte denkwijze geeft. Ik communiceer vlot in het Nederlands (B1, met lessen om verder te verbeteren) en beheers Word, Excel en Outlook uitstekend. Gevestigd in Zwijndrecht, nabij Antwerpen.\n\n## Kernvaardigheden\n- Administratieve ondersteuning & dossierbeheer: offertes, facturatie, opvolging\n- Operationele planning & coördinatie: planning, communicatie met klanten/leveranciers\n- Procesoptimalisatie: signaleren van verbeterpunten, efficiëntere werkwijzen\n- Communicatie: centraal aanspreekpunt, vlot Nederlands (B1), Engels (professioneel), Turks (moedertaal)\n- Software: Word, Excel, Outlook, Google Workspace, WordPress, Elementor\n- Technisch: SEO, GEO, content management, webontwikkeling (AngularJS, JavaScript)\n\n## Ervaring\n\n### Junior Digital Marketer — Episto (Remote), 2026–heden\n- Administratieve en operationele ondersteuning van management: beheer van dossiers, opvolging van offertes en facturatie\n- Coördinatie met klanten, leveranciers en interne teams als centraal aanspreekpunt\n- Opstellen en beheren van content in WordPress, inclusief planning en publicatie\n- Uitvoeren van SEO-optimalisaties en rapporteren van prestaties via Google Analytics, Search Console, SEMrush en Ahrefs\n\n### Warehouse & Logistics — Katoen Natie (Antwerpen), 2025–2026\n- Nauwkeurig en efficiënt werken in een hoogvolume, snelle logistieke omgeving\n- Teamcoördinatie en communicatie met verschillende afdelingen\n\n### Front-End Developer — ViviDoctor (België), 2018–2019\n- Ontwikkelen en optimaliseren van front-end functionaliteiten voor een webapplicatie in de gezondheidszorg (AngularJS, JavaScript)\n- Samenwerken met cross-functionele teams en bijdragen aan projectplanning\n\n## Projecten\n\n### mirook.com — Website Ontwerp, SEO & GEO (2025–heden)\n- Ontworpen en gebouwd van een multi-page WordPress-site (Elementor, Astra) voor een Belgische jeugdschaakkampioen: volledige sitestructuur, on-page SEO en sociale media-integratie\n- Gestructureerde data (JSON-LD schema) en entity/knowledge-graph markup geïmplementeerd voor betere zichtbaarheid\n- Technische SEO/GEO-audits uitgevoerd en search-health score meetbaar verbeterd\n\n## Opleiding\n- Karel de Grote Hogeschool, Antwerpen — Vakken in Toegepaste Informatica (2022–2025)\n- Celal Bayar University, Turkije — Vakken in Computerwetenschappen (2012–2016)\n- Diyarbakır Anatolian High School, Turkije — Middelbareschooldiploma (2012)\n\n## Referenties\nOp aanvraag beschikbaar.",
 "fmt": 2
}